IndexMapping/mapcfunctions.cp310-win_amd64.pyd
IndexMapping/mapping.cp310-win_amd64.pyd
IndexMapping-1.0.2.data/data/lib/site-packages/IndexMapping/LICENSE
IndexMapping-1.0.2.data/data/lib/site-packages/IndexMapping/README.md
IndexMapping-1.0.2.data/data/lib/site-packages/IndexMapping/__init__.pxd
IndexMapping-1.0.2.data/data/lib/site-packages/IndexMapping/__init__.py
IndexMapping-1.0.2.data/data/lib/site-packages/IndexMapping/mapc.c
IndexMapping-1.0.2.data/data/lib/site-packages/IndexMapping/mapcfunctions.pyx
IndexMapping-1.0.2.data/data/lib/site-packages/IndexMapping/mapping.pxd
IndexMapping-1.0.2.data/data/lib/site-packages/IndexMapping/mapping.pyx
IndexMapping-1.0.2.data/data/lib/site-packages/IndexMapping/pyproject.toml
IndexMapping-1.0.2.data/data/lib/site-packages/IndexMapping/requirements.txt
IndexMapping-1.0.2.data/data/lib/site-packages/IndexMapping/setup.cfg
IndexMapping-1.0.2.data/data/lib/site-packages/IndexMapping/setup_mapping.py
IndexMapping-1.0.2.data/data/lib/site-packages/IndexMapping/Assets/A1.png
IndexMapping-1.0.2.data/data/lib/site-packages/IndexMapping/test/__init__.py
IndexMapping-1.0.2.data/data/lib/site-packages/IndexMapping/test/profiling.py
IndexMapping-1.0.2.data/data/lib/site-packages/IndexMapping/test/test_mapping.py
IndexMapping-1.0.2.data/data/lib/site-packages/IndexMapping/test/test_split.py
test/__init__.py
test/profiling.py
test/test_mapping.py
test/test_split.py
IndexMapping-1.0.2.dist-info/LICENSE
IndexMapping-1.0.2.dist-info/METADATA
IndexMapping-1.0.2.dist-info/WHEEL
IndexMapping-1.0.2.dist-info/top_level.txt
IndexMapping-1.0.2.dist-info/RECORD
