Metadata-Version: 2.1
Name: IndexMapping
Version: 1.0.2
Summary: 1D array transpose/conversion
Home-page: https://github.com/yoyoberenguer/IndexMapping
Author: Yoann Berenguer
Author-email: yoyoberenguer@hotmail.com
License: MIT
Project-URL: Bug Reports, https://github.com/yoyoberenguer/IndexMapping/issues
Project-URL: Source, https://github.com/yoyoberenguer/IndexMapping
Keywords: Buffer,transpose,Array indexing,1D array to 3D array,3D array to 1D array
Platform: any
Classifier: Development Status :: 4 - Beta
Classifier: Intended Audience :: Developers
Classifier: Topic :: Software Development :: Build Tools
Classifier: Operating System :: Microsoft :: Windows
Classifier: Programming Language :: Python
Classifier: Programming Language :: Cython
Classifier: Programming Language :: C
Classifier: License :: OSI Approved :: MIT License
Classifier: Programming Language :: Python :: 3.6
Classifier: Programming Language :: Python :: 3.7
Classifier: Programming Language :: Python :: 3.8
Classifier: Programming Language :: Python :: 3.9
Classifier: Programming Language :: Python :: 3.10
Classifier: Topic :: Software Development :: Libraries :: Python Modules
Requires-Python: >=3.0
Requires-Dist: setuptools (>=49.2.1)
Requires-Dist: Cython (>=0.28)
